SoleStormCatPY/ClockTimer.py
SoleStormCatPY/GreeNotes.py
SoleStormCatPY/MathSolver.py
SoleStormCatPY/MyEmailClient.py
SoleStormCatPY/SoleStormCatPY.ico
SoleStormCatPY/SoleStormCatPYApp.py
SoleStormCatPY/SystemInfo.py
SoleStormCatPY/WebOpen.py
SoleStormCatPY/__init__.py
SoleStormCatPY/appOpener.py
SoleStormCatPY/files.py
SoleStormCatPY/interactiveShell.py
SoleStormCatPY/sscPyStandalone.py
SoleStormCatPY/terminal.py
SoleStormCatPY/unixtimecon.py
SoleStormCatPY/ClockTimerAssets/timerUP.wav
solestormcatpy-0.6.2024.dist-info/METADATA
solestormcatpy-0.6.2024.dist-info/WHEEL
solestormcatpy-0.6.2024.dist-info/licenses/LICENSE
solestormcatpy-0.6.2024.dist-info/RECORD
