Metadata-Version: 2.1
Name: SoleStormCatPY
Version: 0.6.2024
Summary: SoleStormCatPY is a set of Python apps/scripts that can help you with whatever you need, wether it be your development of a Python script/app, or you just want to mess around for fun, SoleStormCatPY is for you!
Project-URL: Homepage, https://github.com/solestormcat-corp/SoleStormCatPY
Project-URL: Bug Tracker, https://github.com/solestormcat-corp/SoleStormCatPY/issues
Author-email: SoleStormCat Corp <solestormcat.corp@proton.me>
License-File: LICENSE
Classifier: License :: OSI Approved :: MIT License
Classifier: Operating System :: OS Independent
Classifier: Programming Language :: Python :: 3
Requires-Python: >=3.7
